dexat/__init__.py
dexat-1.dist-info/METADATA
dexat-1.dist-info/WHEEL
dexat-1.dist-info/top_level.txt
dexat-1.dist-info/RECORD
