Metadata-Version: 2.1
Name: dexat
Version: 1
Summary: Dependency confiuse Attack
Author: dex tester
Author-email: <bughunt250@gmail.com
Requires-Dist: requests
Requires-Dist: discord
